tsidpy/__init__.py
tsidpy/basen.py
tsidpy/py.typed
tsidpy/tsid.py
tsidpy-1.1.5.dist-info/LICENSE
tsidpy-1.1.5.dist-info/METADATA
tsidpy-1.1.5.dist-info/WHEEL
tsidpy-1.1.5.dist-info/top_level.txt
tsidpy-1.1.5.dist-info/RECORD
