Metadata-Version: 2.1
Name: tsidpy
Version: 1.1.5
Summary: A Python library for generating Time-Sorted Unique Identifiers (TSID)
Author-email: Luis Medel <luis@luismedel.com>
Project-URL: Homepage, https://github.com/luismedel/tsid-python
Classifier: Intended Audience :: Developers
Classifier: Programming Language :: Python :: 3
Classifier: License :: OSI Approved :: MIT License
Classifier: Operating System :: OS Independent
Classifier: Typing :: Typed
Requires-Python: >=3.7
License-File: LICENSE
